kitab/__init__.py
kitab/utils.py
kitab/api/__init__.py
kitab/api/app.py
kitab/db/__init__.py
kitab/db/db_credentials.py
kitab/db/db_info.py
kitab/db/functions.py
kitab/db/get_data.py
kitab/db/sql_interactions.py
kitab/logger/__init__.py
kitab/logger/logger.py
kitab/recommendation_model/__init__.py
kitab/recommendation_model/models.py
kitab-0.0.28.dist-info/LICENSE
kitab-0.0.28.dist-info/METADATA
kitab-0.0.28.dist-info/WHEEL
kitab-0.0.28.dist-info/top_level.txt
kitab-0.0.28.dist-info/RECORD
