Metadata-Version: 2.1
Name: kitab
Version: 0.0.28
Summary: A package for book recommendation.
Author: Alexander Shahramanyan, Anna Charchyan, Yeva Manukyan, Lilith Asminian, Maria Petrosyan
Classifier: Programming Language :: Python :: 3
Classifier: License :: OSI Approved :: MIT License
Classifier: Operating System :: OS Independent
Requires-Python: >=3.9
License-File: LICENSE
Requires-Dist: pandas
Requires-Dist: fastapi
Requires-Dist: sentence-transformers >=2.6
Requires-Dist: psycopg2-binary
Requires-Dist: pgvector
Requires-Dist: python-dotenv
Requires-Dist: tqdm
